tree_timer/__init__.py
tree_timer/tree_timer.py
tree_timer-0.1.0.dist-info/licenses/LICENSE
tree_timer-0.1.0.dist-info/METADATA
tree_timer-0.1.0.dist-info/WHEEL
tree_timer-0.1.0.dist-info/top_level.txt
tree_timer-0.1.0.dist-info/RECORD
