Metadata-Version: 2.4
Name: tree-timer
Version: 0.1.0
Summary: A hierarchical performance timer for structured profiling
Author-email: Takamu Kaneko <19400343+okenakt@users.noreply.github.com>
License: MIT License
Project-URL: Homepage, https://github.com/okenakt/tree-timer
Project-URL: Repository, https://github.com/okenakt/tree-timer
Project-URL: Documentation, https://github.com/okenakt/tree-timer#readme
Project-URL: Issues, https://github.com/okenakt/tree-timer/issues
Keywords: timer,timing,performance,profiling,benchmark,tree,nested,structured,context-manager,with-statement
Classifier: Development Status :: 4 - Beta
Classifier: Intended Audience :: Developers
Classifier: Intended Audience :: Science/Research
Classifier: Topic :: Software Development :: Libraries
Classifier: Topic :: System :: Benchmark
Classifier: Topic :: Utilities
Classifier: License :: OSI Approved :: MIT License
Classifier: Programming Language :: Python
Classifier: Programming Language :: Python :: 3
Classifier: Programming Language :: Python :: 3.11
Classifier: Programming Language :: Python :: 3.12
Classifier: Operating System :: OS Independent
Requires-Python: >=3.11
License-File: LICENSE
Dynamic: license-file
